xtra/__init__.py
xtra/my_class.py
xtra-1.0.0.dist-info/LICENSE
xtra-1.0.0.dist-info/METADATA
xtra-1.0.0.dist-info/WHEEL
xtra-1.0.0.dist-info/top_level.txt
xtra-1.0.0.dist-info/RECORD
