Metadata-Version: 2.1
Name: xtra
Version: 1.0.0
Summary: Taken By Trakos (: 
Home-page: https://github.com/mhdeiiking/xtra
Author: king-trakos
Author-email: trakosiraq@gmail.com
License: UNKNOWN
Project-URL: Bug Tracker, https://github.com/mhdeiiking/xtra/issues
Platform: UNKNOWN
Classifier: Programming Language :: Python :: 3
Classifier: License :: OSI Approved :: MIT License
Classifier: Operating System :: OS Independent
Requires-Python: >=3.8
License-File: LICENSE
